getaltbranches/__init__.py
getaltbranches/main.py
getaltbranches-0.1.0.dist-info/LICENSE
getaltbranches-0.1.0.dist-info/METADATA
getaltbranches-0.1.0.dist-info/WHEEL
getaltbranches-0.1.0.dist-info/top_level.txt
getaltbranches-0.1.0.dist-info/RECORD
