Metadata-Version: 2.1
Name: getaltbranches
Version: 0.1.0
Summary: A lightweight library for getting branches from public REST API
Home-page: https://github.com/aliksandrion/get_alt_branch
Author: Alexander Seropyan
Author-email: aliksandrion@gmail.com
Classifier: Programming Language :: Python :: 3
Classifier: License :: OSI Approved :: MIT License
Classifier: Operating System :: OS Independent
License-File: LICENSE
Requires-Dist: requests
